condoAccess/__init__.py
condoAccess/main.py
condoAccess/visitantes.py
condoAccess/visitas.py
condoAccess/database/__init__.py
condoAccess/database/database.py
condoAccess-0.0.2.dist-info/METADATA
condoAccess-0.0.2.dist-info/WHEEL
condoAccess-0.0.2.dist-info/top_level.txt
condoAccess-0.0.2.dist-info/RECORD
