Metadata-Version: 2.1
Name: condoAccess
Version: 0.0.2
Summary: Sistema de gerenciamento de entrada e saída de condomínio.
Home-page: https://github.com/Adonis071/gerenciamento_de_portaria.git
Author: Adonis Pantoja
Author-email: adonisruis07@gmail.com
Requires-Python: >=3.8
